mime_codec/__init__.py
mime_codec/__main__.py
mime_codec/exceptions.py
mime_codec/mime_codec.py
mime_codec/profiles_avc.py
mime_codec/profiles_mp4a.py
mime_codec/webm_mime_types.py
mime_codec/binaries/ffprobe
mime_codec/binaries/ffprobe.exe
Mime_Codec-0.1.2.dist-info/LICENSE
Mime_Codec-0.1.2.dist-info/METADATA
Mime_Codec-0.1.2.dist-info/WHEEL
Mime_Codec-0.1.2.dist-info/top_level.txt
Mime_Codec-0.1.2.dist-info/RECORD
