Metadata-Version: 2.1
Name: Mime-Codec
Version: 0.1.2
Summary: get mime codecs for media purposes
Home-page: https://github.com/skillor/mime-codec
Author: skillor
Author-email: skillor@gmx.net
License: MIT
Keywords: mime,codec,mime-codec,mediasource
Platform: UNKNOWN
Classifier: Programming Language :: Python :: 3 :: Only
Classifier: Programming Language :: Python :: 3.9
Classifier: Topic :: Internet
Requires-Python: >=3
License-File: LICENSE
Requires-Dist: ffmpeg-python (==0.2.0)
